openst/__init__.py
openst/__main__.py
openst/alignment/__init__.py
openst/alignment/apply_transform.py
openst/alignment/feature_matching.py
openst/alignment/fiducial_detection.py
openst/alignment/manual_pairwise_aligner.py
openst/alignment/pairwise_aligner.py
openst/alignment/transcript_assign.py
openst/alignment/transformation.py
openst/cli.py
openst/metadata/__init__.py
openst/metadata/classes/__init__.py
openst/metadata/classes/base.py
openst/metadata/classes/pairwise_alignment.py
openst/metadata/classes/segmentation.py
openst/metadata/example_json.json
openst/metadata/report.py
openst/metadata/templates/pairwise_alignment.html
openst/preprocessing/CUT/README.md
openst/preprocessing/CUT/__init__.py
openst/preprocessing/CUT/models/__init__.py
openst/preprocessing/CUT/models/base_model.py
openst/preprocessing/CUT/models/cut_model.py
openst/preprocessing/CUT/models/networks.py
openst/preprocessing/CUT/models/patchnce.py
openst/preprocessing/CUT/models/template_model.py
openst/preprocessing/CUT/options/__init__.py
openst/preprocessing/CUT/options/base_options.py
openst/preprocessing/CUT/options/test_options.py
openst/preprocessing/CUT/util/__init__.py
openst/preprocessing/CUT/util/util.py
openst/preprocessing/__init__.py
openst/preprocessing/barcode_preprocessing.py
openst/preprocessing/flowcell_map.py
openst/preprocessing/image_preprocess.py
openst/preprocessing/image_stitch.py
openst/preprocessing/imagej_macros/axio_stitch.ijm
openst/preprocessing/imagej_macros/keyence_stitch.ijm
openst/preprocessing/merge_modalities.py
openst/preprocessing/spatial_stitch.py
openst/segmentation/__init__.py
openst/segmentation/segment.py
openst/segmentation/segment_merge.py
openst/threed/__init__.py
openst/threed/from_3d_registration.py
openst/threed/to_3d_registration.py
openst/utils/__init__.py
openst/utils/file.py
openst/utils/from_spacemake.py
openst/utils/pimage.py
openst/utils/points.py
openst/utils/preview.py
openst/utils/pseudoimage.py
openst/utils/scanpy/__init__.py
openst-0.2.3.dist-info/LICENSE
openst-0.2.3.dist-info/METADATA
openst-0.2.3.dist-info/WHEEL
openst-0.2.3.dist-info/entry_points.txt
openst-0.2.3.dist-info/RECORD
