Metadata-Version: 2.1
Name: openst
Version: 0.2.3
Summary: The computational pipeline for the Open-ST method.
License: GPL-2.0
Author: Daniel León-Periñán
Author-email: daniel.leonperinan@mdc-berlin.de
Maintainer: Daniel León-Periñán
Maintainer-email: daniel.leonperinan@mdc-berlin.de
Requires-Python: >3.8,<3.12
Classifier: Development Status :: 5 - Production/Stable
Classifier: Environment :: Console
Classifier: Intended Audience :: Developers
Classifier: Intended Audience :: Science/Research
Classifier: License :: OSI Approved :: GNU General Public License v2 (GPLv2)
Classifier: Natural Language :: English
Classifier: Operating System :: MacOS :: MacOS X
Classifier: Operating System :: Microsoft :: Windows
Classifier: Operating System :: POSIX :: Linux
Classifier: Programming Language :: Python :: 3
Classifier: Programming Language :: Python :: 3.9
Classifier: Programming Language :: Python :: 3.10
Classifier: Programming Language :: Python :: 3.11
Classifier: Programming Language :: Python :: 3.8
Classifier: Topic :: Scientific/Engineering :: Bio-Informatics
Classifier: Topic :: Scientific/Engineering :: Visualization
Requires-Dist: anndata (>=0.7.4)
Requires-Dist: cellpose (>=2.2.3)
Requires-Dist: dask-image
Requires-Dist: dask[array]
Requires-Dist: dnaio (>=1.2.0)
Requires-Dist: h5py (>=3)
Requires-Dist: joblib
Requires-Dist: kornia (>=0.7.0)
Requires-Dist: matplotlib (>=3.4)
Requires-Dist: natsort
Requires-Dist: numpy (>=1.17.0)
Requires-Dist: ome-zarr (>=0.8.2)
Requires-Dist: opencv-python (>=4.8.0.76)
Requires-Dist: pandas (>=1.0)
Requires-Dist: pyqt5 (==5.15.9)
Requires-Dist: pyqt5-qt5 (==5.15.2)
Requires-Dist: pyqt5-sip (==12.12.2)
Requires-Dist: pyqtgraph (>=0.13.3)
Requires-Dist: scikit-image (==0.19.3)
Requires-Dist: scikit-learn (>=0.24)
Requires-Dist: scipy (>=1.4)
Requires-Dist: tqdm
Project-URL: Documentation, https://rajewsky-lab.github.io/openst/
Project-URL: Home-page, https://rajewsky-lab.github.io/openst
Project-URL: Source, https://github.com/rajewsky-lab/openst
Project-URL: Twitter, https://twitter.com/open_sts
